notint/__init__.py
notint-1.0.1.dist-info/LICENSE
notint-1.0.1.dist-info/METADATA
notint-1.0.1.dist-info/WHEEL
notint-1.0.1.dist-info/top_level.txt
notint-1.0.1.dist-info/RECORD
