Metadata-Version: 2.1
Name: notint
Version: 1.0.1
Summary: This is not an integer
Home-page: https://github.com/donno2048/notint
Author: Elisha Hollander
License: MIT
Platform: UNKNOWN
Classifier: Programming Language :: Python :: 3
